chisel/__init__.py
chisel/core.py
kingdom_chisel-0.0.1.dev2.dist-info/LICENSE
kingdom_chisel-0.0.1.dev2.dist-info/WHEEL
kingdom_chisel-0.0.1.dev2.dist-info/METADATA
kingdom_chisel-0.0.1.dev2.dist-info/RECORD
